CONTRIBUTING.md
COPYING
MANIFEST.in
Makefile
NEWS.md
README.md
SECURITY.md
acl.c
posix1e.pyi
py.typed
setup.cfg
setup.py
doc/conf.py
doc/contributing.md
doc/implementation.rst
doc/index.rst
doc/module.rst
doc/news.md
doc/readme.md
doc/security.md
pylibacl.egg-info/PKG-INFO
pylibacl.egg-info/SOURCES.txt
pylibacl.egg-info/dependency_links.txt
pylibacl.egg-info/not-zip-safe
pylibacl.egg-info/top_level.txt
tests/test_acls.py