Metadata-Version: 2.1
Name: pylibacl
Version: 0.7.3
Summary: POSIX.1e ACLs for python
Home-page: https://pylibacl.k1024.org/
Author: Iustin Pop
Author-email: iustin@k1024.org
License: LGPL
Project-URL: Bug Tracker, https://github.com/iustin/pylibacl/issues
Classifier: Development Status :: 5 - Production/Stable
Classifier: Intended Audience :: Developers
Classifier: License :: OSI Approved :: GNU Lesser General Public License v2 or later (LGPLv2+)
Classifier: Programming Language :: Python :: 3 :: Only
Classifier: Programming Language :: Python :: Implementation :: CPython
Classifier: Programming Language :: Python :: Implementation :: PyPy
Classifier: Operating System :: POSIX :: BSD :: FreeBSD
Classifier: Operating System :: POSIX :: Linux
Classifier: Topic :: Software Development :: Libraries :: Python Modules
Classifier: Topic :: System :: Filesystems
Requires-Python: >=3.7
License-File: COPYING
